{
  "video_name": "kitchen_03",
  "dataset": "robot",
  "mode": "incremental",
  "analyzed_at": "2026-02-05T10:34:31.689016",
  "nstf_path": "data/nstf_graphs/robot/kitchen_03_nstf.pkl",
  "errors": [],
  "warnings": [],
  "stats": {
    "num_procedures": 31,
    "steps": {
      "total": 120,
      "min": 1,
      "max": 8,
      "avg": 3.870967741935484,
      "empty_count": 0
    },
    "dag": {
      "nodes_total": 182,
      "edges_total": 152,
      "empty_dag_count": 0
    },
    "episodic_links": {
      "total": 57,
      "min": 1,
      "max": 10,
      "avg": 1.8387096774193548
    },
    "valid_dags": 31,
    "steps_dag_consistent": 31,
    "edge_statistics": {
      "total_edges": 152,
      "count_range": [
        1,
        2
      ],
      "uniform_count_procs": 29,
      "uniform_prob_procs": 31,
      "linear_dags": 30,
      "branching_dags": 1
    },
    "episodic_coverage": {
      "total_clips": 74,
      "referenced_clips": 57,
      "coverage_pct": 77.02702702702703
    },
    "goal_quality": {
      "total": 31,
      "vague": 1,
      "specific": 16
    },
    "character_mapping": {
      "total": 67,
      "face_count": 2,
      "voice_count": 65,
      "unique_persons": 13
    }
  }
}